Workbook

Sheet Age & Gender Revenue
A1: REVENUE BY GENDER/ AGE
A3: Age/Gender | B3: Total Spend
A4: Female | B4: 75191
A5: 18-27 | B5: 13644
A6: 28-37 | B6: 14415
A7: 38-47 | B7: 14742
A8: 48-57 | B8: 14906
A9: 58-67 | B9: 13307
A10: 68-77 | B10: 4177
A11: Male | B11: 157890
A12: 18-27 | B12: 29658
A13: 28-37 | B13: 30503
A14: 38-47 | B14: 27581
A15: 48-57 | B15: 31869
... A18: Grand Total | B18: 233081

Sheet Subscription Revenue
A1: REVENUE BASED ON SUBSCRIPTION
A2: Subscription Status | B2: Total Revenue | C2: AOV | D2: Tot orders
A3: No | B3: 170436 | C3: 59.865121 | D3: 0.73
A4: Yes | B4: 62645 | C4: 59.491928 | D4: 0.27
A5: Grand Total | B5: 233081 | C5: 59.764359 | D5: 1

Sheet Payment Methods
A1: PAYMENT METHODS MOSTLY
A2: Row Labels | B2: Count of Payment Method | C2: Count of Payment Method2 | E2: =100-17.18 -> 82.82
A3: PayPal | B3: 677 | C3: 0.17358974 | E3: 82.82% OF THE purchases are cashless while only 17.18% is by cash
A4: Credit Card | B4: 671 | C4: 0.17205128
A5: Cash | B5: 670 | C5: 0.17179487
A6: Debit Card | B6: 636 | C6: 0.16307692
A7: Venmo | B7: 634 | C7: 0.1625641
A8: Bank Transfer | B8: 612 | C8: 0.15692308
A9: Grand Total | B9: 3900 | C9: 1

Sheet Purchase Frequency
A1: Row Labels | B1: Count of Frequency of Purchases
A2: Annually | B2: 572
A3: Bi-Weekly | B3: 547
A4: Every 3 Months | B4: 584
A5: Fortnightly | B5: 542
A6: Monthly | B6: 553
A7: Quarterly | B7: 563
A8: Weekly | B8: 539
A9: Grand Total | B9: 3900

Sheet Location Revenue
D2: Location | E2: Revenue
A3: locations | B3: Revenue by location | D3: Alabama | E3: =SUMIF('Shopping Data'!$G$2:$G$3901,D3,'Shopping Data'!$F$2:$F$3901) -> 5261
A4: Alabama | B4: 5261 | D4: Alaska | E4: =SUMIF('Shopping Data'!$G$2:$G$3901,D4,'Shopping Data'!$F$2:$F$3901) -> 4867
A5: California | B5: 5605 | D5: Arizona | E5: =SUMIF('Shopping Data'!$G$2:$G$3901,D5,'Shopping Data'!$F$2:$F$3901) -> 4326
A6: Idaho | B6: 5587 | D6: Arkansas | E6: =SUMIF('Shopping Data'!$G$2:$G$3901,D6,'Shopping Data'!$F$2:$F$3901) -> 4828
A7: Illinois | B7: 5617 | D7: California | E7: =SUMIF('Shopping Data'!$G$2:$G$3901,D7,'Shopping Data'!$F$2:$F$3901) -> 5605
A8: Montana | B8: 5784 | D8: Colorado | E8: =SUMIF('Shopping Data'!$G$2:$G$3901,D8,'Shopping Data'!$F$2:$F$3901) -> 4222
A9: Nebraska | B9: 5172 | D9: Connecticut | E9: =SUMIF('Shopping Data'!$G$2:$G$3901,D9,'Shopping Data'!$F$2:$F$3901) -> 4226
A10: Nevada | B10: 5514 | D10: Delaware | E10: =SUMIF('Shopping Data'!$G$2:$G$3901,D10,'Shopping Data'!$F$2:$F$3901) -> 4758
A11: New York | B11: 5257 | D11: Florida | E11: =SUMIF('Shopping Data'!$G$2:$G$3901,D11,'Shopping Data'!$F$2:$F$3901) -> 3798
A12: North Dakota | B12: 5220 | D12: Georgia | E12: =SUMIF('Shopping Data'!$G$2:$G$3901,D12,'Shopping Data'!$F$2:$F$3901) -> 4645
A13: West Virginia | B13: 5174 | D13: Hawaii | E13: =SUMIF('Shopping Data'!$G$2:$G$3901,D13,'Shopping Data'!$F$2:$F$3901) -> 3752
D14: Idaho | E14: =SUMIF('Shopping Data'!$G$2:$G$3901,D14,'Shopping Data'!$F$2:$F$3901) -> 5587
D15: Illinois | E15: =SUMIF('Shopping Data'!$G$2:$G$3901,D15,'Shopping Data'!$F$2:$F$3901) -> 5617
D16: Indiana | E16: =SUMIF('Shopping Data'!$G$2:$G$3901,D16,'Shopping Data'!$F$2:$F$3901) -> 4655
D17: Iowa | E17: =SUMIF('Shopping Data'!$G$2:$G$3901,D17,'Shopping Data'!$F$2:$F$3901) -> 4201
D18: Kansas | E18: =SUMIF('Shopping Data'!$G$2:$G$3901,D18,'Shopping Data'!$F$2:$F$3901) -> 3437
D19: Kentucky | E19: =SUMIF('Shopping Data'!$G$2:$G$3901,D19,'Shopping Data'!$F$2:$F$3901) -> 4402
D20: Louisiana | E20: =SUMIF('Shopping Data'!$G$2:$G$3901,D20,'Shopping Data'!$F$2:$F$3901) -> 4848
D21: Maine | E21: =SUMIF('Shopping Data'!$G$2:$G$3901,D21,'Shopping Data'!$F$2:$F$3901) -> 4388
D22: Maryland | E22: =SUMIF('Shopping Data'!$G$2:$G$3901,D22,'Shopping Data'!$F$2:$F$3901) -> 4795
D23: Massachusetts | E23: =SUMIF('Shopping Data'!$G$2:$G$3901,D23,'Shopping Data'!$F$2:$F$3901) -> 4384
D24: Michigan | E24: =SUMIF('Shopping Data'!$G$2:$G$3901,D24,'Shopping Data'!$F$2:$F$3901) -> 4533
D25: Minnesota | E25: =SUMIF('Shopping Data'!$G$2:$G$3901,D25,'Shopping Data'!$F$2:$F$3901) -> 4977
... D52: Wyoming | E52: =SUMIF('Shopping Data'!$G$2:$G$3901,D52,'Shopping Data'!$F$2:$F$3901) -> 4309

Sheet Season Revenue
A2: Row Labels | B2: tot revenue | C2: % revenue
A3: Fall | B3: 60018 | C3: 0.25749847
A4: Spring | B4: 58679 | C4: 0.25175368
A5: Summer | B5: 55777 | C5: 0.23930307
A6: Winter | B6: 58607 | C6: 0.25144478
A7: Grand Total | B7: 233081 | C7: 1

Sheet Category Revenue
A3: Category | B3: Tot Revenue | C3: % revenue
A4: Clothing | B4: 104264 | C4: 0.44732947
A5: Accessories | B5: 74200 | C5: 0.31834427
A6: Footwear | B6: 36093 | C6: 0.15485175
A7: Outerwear | B7: 18524 | C7: 0.079474517
A8: Grand Total | B8: 233081 | C8: 1

Sheet Item Revenue
A2: To 10 items sales | B2: Revenue by item
A3: Blouse | B3: 10410
A4: Shirt | B4: 10332
A5: Dress | B5: 10320
A6: Pants | B6: 10090
A7: Jewelry | B7: 10010
A8: Sunglasses | B8: 9649
A9: Belt | B9: 9635
A10: Scarf | B10: 9561
A11: Sweater | B11: 9462
A12: Shorts | B12: 9433
A13: Grand Total | B13: 98902

Sheet Color Revenue
A1: Colour | B1: tot revenue
A2: Green | B2: 11104
A3: Teal | B3: 10459
A4: Yellow | B4: 10308
A5: Olive | B5: 10292
A6: Cyan | B6: 10274
A7: Violet | B7: 10245
A8: Gray | B8: 9936
A9: Silver | B9: 9832
A10: Black | B10: 9753
A11: Maroon | B11: 9405
A12: Orange | B12: 9377
A13: Charcoal | B13: 9277
... A26: Turquoise | B26: 8064
A27: (blank)
A28: Grand Total | B28: 233081

Sheet Size Revenue
A1: Size | B1: tot revenue | C1: % revenue
A2: M | B2: 105167 | C2: 0.45120366
A3: L | B3: 61667 | C3: 0.26457326
A4: S | B4: 40468 | C4: 0.17362205
A5: XL | B5: 25779 | C5: 0.11060104
A6: Grand Total | B6: 233081 | C6: 1

Sheet Discount Revenue
A3: Discounted | B3: TOt Revenue | F3: Summary KPI's | G3: values
A4: No | B4: 133670 | F4: discounted revenue | G4: =GETPIVOTDATA("Purchase Amount (USD)",$A$3,"Discount Applied","Yes") -> 99411
A5: Yes | B5: 99411 | F5: undiscounted revenue | G5: =GETPIVOTDATA("Purchase Amount (USD)",$A$3,"Discount Applied","No") -> 133670
A6: Grand Total | B6: 233081 | F6: Aov discounted | G6: =GETPIVOTDATA("Purchase Amount (USD)",'Discount AOV'!$A$3,"Discount Applied","Yes") -> 59.27907
F7: Aov undiscounted | G7: =GETPIVOTDATA("Purchase Amount (USD)",'Discount AOV'!$A$3,"Discount Applied","No") -> 60.130454
F8: avrage Rating | G8: =AVERAGE(Table2[Review Rating]) -> 3.7308718

Sheet Discount AOV
A3: Discounted | B3: AOV
A4: No | B4: 60.130454
A5: Yes | B5: 59.27907
A6: Grand Total | B6: 59.764359

Sheet Average Rating
A3: Category | B3: Avrage Rating | D3: KPI Validation | E3: Value
A4: Accessories | B4: 3.7470161 | D4: Weighted overall average | E4: =AVERAGE('Shopping Data'!K2:K3901) -> 3.7308718
A5: Clothing | B5: 3.7044905 | D5: Dashboard Insights!J5 | E5: Dashboard Insights!J6
A6: Footwear | B6: 3.7841402
A7: Outerwear | B7: 3.712037
A8: Grand Total | B8: 3.7308718
A11: Weighted Raw-Data Average | B11: =AVERAGE('Shopping Data'!K2:K3901) -> 3.7308718

Sheet Rating Distribution
A1: Review Rating | B1: % reviews
A2: 2.5 | B2: 0.016923077
A3: 2.6 | B3: 0.03974359
A4: 2.7 | B4: 0.038205128
A5: 2.8 | B5: 0.034102564
A6: 2.9 | B6: 0.041794872
A7: 3 | B7: 0.041282051
A8: 3.1 | B8: 0.064102564
A9: 3.2 | B9: 0.038205128
A10: 3.3 | B10: 0.037948718
A11: 3.4 | B11: 0.046410256
A12: 3.5 | B12: 0.039487179
A13: 3.6 | B13: 0.037435897
... A27: 5 | B27: 0.017179487
A28: Grand Total | B28: 1

Sheet Key KPIs

Sheet Payment Method Counts
A3: Row Labels | B3: Count of Payment Method
A4: PayPal | B4: 677
A5: Credit Card | B5: 671
A6: Cash | B6: 670
A7: Debit Card | B7: 636
A8: Venmo | B8: 634
A9: Bank Transfer | B9: 612
A10: Grand Total | B10: 3900

Sheet Shopping Data
A1: Customer ID | B1: Age | C1: Gender | D1: Item Purchased | E1: Category | F1: Purchase Amount (USD) | G1: Location | H1: Size | I1: Color | J1: Season | K1: Review Rating | L1: Subscription Status | M1: Discount Applied | N1: Previous Purchases | O1: Payment Method | P1: Frequency of Purchases | Q1: Total _Sales
A2: 1 | B2: 55 | C2: Male | D2: Blouse | E2: Clothing | F2: 53 | G2: Kentucky | H2: L | I2: Gray | J2: Winter | K2: 3.1 | L2: Yes | M2: Yes | N2: 14 | O2: Venmo | P2: Fortnightly | Q2: =SUM(Table2[Purchase Amount (USD)]) -> 233081
A3: 2 | B3: 19 | C3: Male | D3: Sweater | E3: Clothing | F3: 64 | G3: Maine | H3: L | I3: Maroon | J3: Winter | K3: 3.1 | L3: Yes | M3: Yes | N3: 2 | O3: Cash | P3: Fortnightly
A4: 3 | B4: 50 | C4: Male | D4: Jeans | E4: Clothing | F4: 73 | G4: Massachusetts | H4: S | I4: Maroon | J4: Spring | K4: 3.1 | L4: Yes | M4: Yes | N4: 23 | O4: Credit Card | P4: Weekly
A5: 4 | B5: 21 | C5: Male | D5: Sandals | E5: Footwear | F5: 90 | G5: Rhode Island | H5: M | I5: Maroon | J5: Spring | K5: 3.1 | L5: Yes | M5: Yes | N5: 49 | O5: PayPal | P5: Weekly
A6: 5 | B6: 45 | C6: Male | D6: Blouse | E6: Clothing | F6: 49 | G6: Oregon | H6: M | I6: Turquoise | J6: Spring | K6: 3.1 | L6: Yes | M6: Yes | N6: 31 | O6: PayPal | P6: Annually
A7: 6 | B7: 46 | C7: Male | D7: Sneakers | E7: Footwear | F7: 20 | G7: Wyoming | H7: M | I7: White | J7: Summer | K7: 3.1 | L7: Yes | M7: Yes | N7: 14 | O7: Venmo | P7: Weekly
A8: 7 | B8: 63 | C8: Male | D8: Shirt | E8: Clothing | F8: 85 | G8: Montana | H8: M | I8: Gray | J8: Fall | K8: 3.1 | L8: Yes | M8: Yes | N8: 49 | O8: Cash | P8: Quarterly
A9: 8 | B9: 27 | C9: Male | D9: Shorts | E9: Clothing | F9: 34 | G9: Louisiana | H9: L | I9: Charcoal | J9: Winter | K9: 3.1 | L9: Yes | M9: Yes | N9: 19 | O9: Credit Card | P9: Weekly
A10: 9 | B10: 26 | C10: Male | D10: Coat | E10: Outerwear | F10: 97 | G10: West Virginia | H10: L | I10: Silver | J10: Summer | K10: 3.1 | L10: Yes | M10: Yes | N10: 8 | O10: Venmo | P10: Annually
A11: 10 | B11: 57 | C11: Male | D11: Handbag | E11: Accessories | F11: 31 | G11: Missouri | H11: M | I11: Pink | J11: Spring | K11: 3.1 | L11: Yes | M11: Yes | N11: 4 | O11: Cash | P11: Quarterly
A12: 11 | B12: 53 | C12: Male | D12: Shoes | E12: Footwear | F12: 34 | G12: Arkansas | H12: L | I12: Purple | J12: Fall | K12: 3.1 | L12: Yes | M12: Yes | N12: 26 | O12: Bank Transfer | P12: Bi-Weekly
A13: 12 | B13: 30 | C13: Male | D13: Shorts | E13: Clothing | F13: 68 | G13: Hawaii | H13: S | I13: Olive | J13: Winter | K13: 3.1 | L13: Yes | M13: Yes | N13: 10 | O13: Bank Transfer | P13: Fortnightly
A14: 13 | B14: 61 | C14: Male | D14: Coat | E14: Outerwear | F14: 72 | G14: Delaware | H14: M | I14: Gold | J14: Winter | K14: 3.1 | L14: Yes | M14: Yes | N14: 37 | O14: Venmo | P14: Fortnightly
... A3901: 3900 | B3901: 52 | C3901: Female | D3901: Handbag | E3901: Accessories | F3901: 81 | G3901: California | H3901: M | I3901: Beige | J3901: Spring | K3901: 3.1 | L3901: No | M3901: No | N3901: 33 | O3901: Venmo | P3901: Quarterly
F3902: =SUM(Table2[[#Headers],[#Data],[Purchase Amount (USD)]]) -> 233081

Sheet Dashboard

Sheet Dashboard Insights
A1: SHOPPING BEHAVIOR DASHBOARD INSIGHTS
A5: TOTAL REVENUE | D5: TRANSACTIONS | G5: AVERAGE ORDER VALUE | J5: AVERAGE RATING | M5: MAP REVENUE COVERAGE
A6: =SUM('Shopping Data'!F2:F3901) -> 233081 | D6: =COUNTA('Shopping Data'!A2:A3901) -> 3900 | G6: =A6/D6 -> 59.764359 | J6: =AVERAGE('Shopping Data'!K2:K3901) -> 3.7308718 | M6: =SUM('Location Revenue'!E3:E52)/A6 -> 1
A10: INITIAL FINDINGS
A11: ="• Category concentration: Clothing and Accessories generate "&TEXT(SUM('Category Revenue'!B4:B5)/$A$6,"0.0%")&" of revenue; Clothing alone contributes "&TEXT('Category Revenue'!C4,"0.0%")&"." -> • Category concentration: Clothing and Accessories generate 76.6% of revenue; Clothing alone contributes 44.7%.
A12: ="• Customer mix: Male shoppers contribute "&TEXT('Age & Gender Revenue'!B11/$A$6,"0.0%")&" of revenue, more than twice the female share." -> • Customer mix: Male shoppers contribute 67.7% of revenue, more than twice the female share.
A13: ="• Commercial levers: Subscribers represent "&TEXT('Subscription Revenue'!D4,"0.0%")&" of orders and have a nearly identical AOV ("&TEXT('Subscription Revenue'!C4,"$0.00")&" vs "&TEXT('Subscription Revenue'!C3,"$0.00")&")." -> • Commercial levers: Subscribers represent 27.0% of orders and have a nearly identical AOV ($59.49 vs $59.87).
A14: ="• Discounts do not lift basket size: discounted AOV is "&TEXT('Discount AOV'!B5,"$0.00")&", "&TEXT(1-'Discount AOV'!B5/'Discount AOV'!B4,"0.0%")&" below undiscounted orders." -> • Discounts do not lift basket size: discounted AOV is $59.28, 1.4% below undiscounted orders.
A15: ="• Mix is stable: seasonal revenue ranges only "&TEXT(MAX('Season Revenue'!C3:C6)-MIN('Season Revenue'!C3:C6),"0.0%")&" from highest to lowest; payment usage is also evenly spread." -> • Mix is stable: seasonal revenue ranges only 1.8% from highest to lowest; payment usage is also evenly spread.
A17: REVENUE BY CATEGORY | E17: PAYMENT METHOD MIX | I17: REVENUE BY SEASON | M17: REVENUE BY GENDER
A18: Category | B18: Revenue | C18: Share | E18: Method | F18: Orders | G18: Share | I18: Season | J18: Revenue | K18: Share | M18: Gender | N18: Revenue | O18: Share
A19: Clothing | B19: ='Category Revenue'!B4 -> 104264 | C19: =B19/$A$6 -> 0.44732947 | E19: PayPal | F19: ='Payment Methods'!B3 -> 677 | G19: =F19/$D$6 -> 0.17358974 | I19: Fall | J19: ='Season Revenue'!B3 -> 60018 | K19: =J19/$A$6 -> 0.25749847 | M19: Male | N19: ='Age & Gender Revenue'!B11 -> 157890 | O19: =N19/$A$6 -> 0.67740399
A20: Accessories | B20: ='Category Revenue'!B5 -> 74200 | C20: =B20/$A$6 -> 0.31834427 | E20: Credit Card | F20: ='Payment Methods'!B4 -> 671 | G20: =F20/$D$6 -> 0.17205128 | I20: Spring | J20: ='Season Revenue'!B4 -> 58679 | K20: =J20/$A$6 -> 0.25175368 | M20: Female | N20: ='Age & Gender Revenue'!B4 -> 75191 | O20: =N20/$A$6 -> 0.32259601
A21: Footwear | B21: ='Category Revenue'!B6 -> 36093 | C21: =B21/$A$6 -> 0.15485175 | E21: Cash | F21: ='Payment Methods'!B5 -> 670 | G21: =F21/$D$6 -> 0.17179487 | I21: Summer | J21: ='Season Revenue'!B5 -> 55777 | K21: =J21/$A$6 -> 0.23930307
A22: Outerwear | B22: ='Category Revenue'!B7 -> 18524 | C22: =B22/$A$6 -> 0.079474517 | E22: Debit Card | F22: ='Payment Methods'!B6 -> 636 | G22: =F22/$D$6 -> 0.16307692 | I22: Winter | J22: ='Season Revenue'!B6 -> 58607 | K22: =J22/$A$6 -> 0.25144478
E23: Venmo | F23: ='Payment Methods'!B7 -> 634 | G23: =F23/$D$6 -> 0.1625641
E24: Bank Transfer | F24: ='Payment Methods'!B8 -> 612 | G24: =F24/$D$6 -> 0.15692308

Sheet Chart Data
A1: Age Band | B1: Female | C1: Male | E1: Subscription Status | F1: Revenue | H1: Category | I1: Revenue | K1: Season | L1: Revenue | N1: Discount Applied | O1: Revenue | Q1: Payment Method | R1: Orders
A2: 18–27 | B2: ='Age & Gender Revenue'!B5 -> 13644 | C2: ='Age & Gender Revenue'!B12 -> 29658 | E2: No | F2: ='Subscription Revenue'!B3 -> 170436 | H2: Clothing | I2: ='Category Revenue'!B4 -> 104264 | K2: Fall | L2: ='Season Revenue'!B3 -> 60018 | N2: No | O2: ='Discount Revenue'!B4 -> 133670 | Q2: PayPal | R2: ='Payment Methods'!B3 -> 677
A3: 28–37 | B3: ='Age & Gender Revenue'!B6 -> 14415 | C3: ='Age & Gender Revenue'!B13 -> 30503 | E3: Yes | F3: ='Subscription Revenue'!B4 -> 62645 | H3: Accessories | I3: ='Category Revenue'!B5 -> 74200 | K3: Spring | L3: ='Season Revenue'!B4 -> 58679 | N3: Yes | O3: ='Discount Revenue'!B5 -> 99411 | Q3: Credit Card | R3: ='Payment Methods'!B4 -> 671
A4: 38–47 | B4: ='Age & Gender Revenue'!B7 -> 14742 | C4: ='Age & Gender Revenue'!B14 -> 27581 | H4: Footwear | I4: ='Category Revenue'!B6 -> 36093 | K4: Summer | L4: ='Season Revenue'!B5 -> 55777 | Q4: Cash | R4: ='Payment Methods'!B5 -> 670
A5: 48–57 | B5: ='Age & Gender Revenue'!B8 -> 14906 | C5: ='Age & Gender Revenue'!B15 -> 31869 | H5: Outerwear | I5: ='Category Revenue'!B7 -> 18524 | K5: Winter | L5: ='Season Revenue'!B6 -> 58607 | Q5: Debit Card | R5: ='Payment Methods'!B6 -> 636
A6: 58–67 | B6: ='Age & Gender Revenue'!B9 -> 13307 | C6: ='Age & Gender Revenue'!B16 -> 28875 | Q6: Venmo | R6: ='Payment Methods'!B7 -> 634
A7: 68–77 | B7: ='Age & Gender Revenue'!B10 -> 4177 | C7: ='Age & Gender Revenue'!B17 -> 9404 | Q7: Bank Transfer | R7: ='Payment Methods'!B8 -> 612
